LICENSE
README.md
setup.py
phishing_detector/__init__.py
phishing_detector/phishing_detector.py
phishing_detector.egg-info/PKG-INFO
phishing_detector.egg-info/SOURCES.txt
phishing_detector.egg-info/dependency_links.txt
phishing_detector.egg-info/requires.txt
phishing_detector.egg-info/top_level.txt