Metadata-Version: 2.1
Name: phishing-detector
Version: 0.1.1
Summary: Library that questions whether a site is phishing or not
Home-page: UNKNOWN
Author: ofsenyayla
Author-email: ofaruksenyyla@gmail.com
License: MIT
Keywords: phishing detection
Platform: UNKNOWN
Classifier: Intended Audience :: Developers
Classifier: License :: OSI Approved :: MIT License
Classifier: Programming Language :: Python
Classifier: Programming Language :: Python :: 3
Classifier: Programming Language :: Python :: 3.6
Classifier: Programming Language :: Python :: 3.7
Classifier: Programming Language :: Python :: 3.8
Classifier: Programming Language :: Python :: 3.9
Classifier: Operating System :: OS Independent
License-File: LICENSE
